pb2dict/__init__.py
pb2dict-1.0.0.dist-info/LICENSE
pb2dict-1.0.0.dist-info/METADATA
pb2dict-1.0.0.dist-info/WHEEL
pb2dict-1.0.0.dist-info/top_level.txt
pb2dict-1.0.0.dist-info/RECORD
