Metadata-Version: 2.2
Name: pb2dict
Version: 1.0.0
Summary: Protobuf to dictionary converter.
Home-page: https://github.com/qvecs/pb2dict
Author: Quick Vectors
Author-email: felipe@qvecs.com
License: MIT
Project-URL: Source Code, https://github.com/qvecs/pb2dict
Project-URL: Bug Tracker, https://github.com/qvecs/pb2dict/issues
Classifier: Development Status :: 4 - Beta
Classifier: License :: OSI Approved :: MIT License
Classifier: Programming Language :: Python :: 3
Classifier: Programming Language :: Python :: 3.8
Classifier: Programming Language :: Python :: 3.9
Classifier: Programming Language :: Python :: 3.10
Classifier: Programming Language :: Python :: 3.11
Classifier: Operating System :: OS Independent
Requires-Python: >=3.8
License-File: LICENSE
Requires-Dist: protobuf
Provides-Extra: dev
Requires-Dist: pytest; extra == "dev"
